ParquetLoader/__init__.py
ParquetLoader/loader.py
ParquetLoader/s3.py
tests/__init__.py
tests/filters.py
tests/local.py
tests/minio.py
tests/s3.py
parquet_loader-0.0.4.dist-info/LICENSE
parquet_loader-0.0.4.dist-info/METADATA
parquet_loader-0.0.4.dist-info/WHEEL
parquet_loader-0.0.4.dist-info/top_level.txt
parquet_loader-0.0.4.dist-info/RECORD
