Metadata-Version: 2.1
Name: parquet-loader
Version: 0.0.4
Summary: Parquet file Load and Read from minio & S3
Home-page: https://github.com/Keunyoung-Jung/ParquetLoader
Author: ('keyog',)
Author-email: jgy206@gmail.com
License: Apache License 2.0
Download-URL: https://github.com/Keunyoung-Jung/ParquetLoader
Keywords: parquet,loader,parquetloader
Platform: UNKNOWN
Classifier: Programming Language :: Python :: 3
Classifier: Programming Language :: Python :: 3.2
Classifier: Programming Language :: Python :: 3.3
Classifier: Programming Language :: Python :: 3.4
Classifier: Programming Language :: Python :: 3.5
Classifier: Programming Language :: Python :: 3.6
Classifier: Programming Language :: Python :: 3.7
Requires-Python: >=3
Requires-Dist: pandas (<=1.2.0)
Requires-Dist: fastparquet (==0.8.0)
Requires-Dist: s3fs
